[{"url":"https://stackshare.io/amazon-s3","votes":"2K","followers":"35.4K","stacks":"49.4K","time":"2022-12-28T13:54:16.859Z","tool":"amazon-s3"},{"url":"http://web.archive.org/web/20200305175027/https://stackshare.io/amazon-s3","votes":"2K","followers":"12.6K","stacks":"18.8K","time":"2020-03-05T17:50:27.000Z","tool":"amazon-s3"},{"url":"http://web.archive.org/web/20200804174236/https://stackshare.io/amazon-s3","votes":"2K","followers":"17.7K","stacks":"27.1K","time":"2020-08-04T17:42:36.000Z","tool":"amazon-s3"},{"url":"http://web.archive.org/web/20200120171055/https://stackshare.io/amazon-s3","votes":"2K","followers":"9.9K","stacks":"16K","time":"2020-01-20T17:10:55.000Z","tool":"amazon-s3"},{"url":"http://web.archive.org/web/20200809050238/https://www.stackshare.io/amazon-s3","votes":"2K","followers":"17.7K","stacks":"27.3K","time":"2020-08-09T05:02:38.000Z","tool":"amazon-s3"},{"url":"http://web.archive.org/web/20201124031445/https://www.stackshare.io/amazon-s3","votes":"2K","followers":"20.4K","stacks":"30.9K","time":"2020-11-24T03:14:45.000Z","tool":"amazon-s3"},{"url":"http://web.archive.org/web/20200518060109/https://stackshare.io/amazon-s3","votes":"2K","followers":"17.5K","stacks":"24K","time":"2020-05-18T06:01:09.000Z","tool":"amazon-s3"},{"url":"http://web.archive.org/web/20210419055239/https://stackshare.io/amazon-s3","votes":"2K","followers":"24.7K","stacks":"35.7K","time":"2021-04-19T05:52:39.000Z","tool":"amazon-s3"},{"url":"http://web.archive.org/web/20210303091619/https://stackshare.io/amazon-s3","votes":"2K","followers":"23.3K","stacks":"34.1K","time":"2021-03-03T09:16:19.000Z","tool":"amazon-s3"},{"url":"http://web.archive.org/web/20210514131234/https://www.stackshare.io/amazon-s3","votes":"2K","followers":"25.3K","stacks":"36.3K","time":"2021-05-14T13:12:34.000Z","tool":"amazon-s3"},{"url":"http://web.archive.org/web/20210620144158/https://stackshare.io/amazon-s3","votes":"2K","followers":"25.8K","stacks":"37K","time":"2021-06-20T14:41:58.000Z","tool":"amazon-s3"},{"url":"http://web.archive.org/web/20210816104146/https://stackshare.io/amazon-s3","votes":"2K","followers":"26.8K","stacks":"38.2K","time":"2021-08-16T10:41:46.000Z","tool":"amazon-s3"},{"url":"http://web.archive.org/web/20201127024345/https://stackshare.io/amazon-s3","votes":"2K","followers":"20.5K","stacks":"31K","time":"2020-11-27T02:43:45.000Z","tool":"amazon-s3"},{"url":"http://web.archive.org/web/20211008035021/https://stackshare.io/amazon-s3","votes":"2K","followers":"28.1K","stacks":"39.7K","time":"2021-10-08T03:50:21.000Z","tool":"amazon-s3"},{"url":"http://web.archive.org/web/20220126044428/https://www.stackshare.io/amazon-s3","votes":"2K","followers":"30.1K","stacks":"41.8K","time":"2022-01-26T04:44:28.000Z","tool":"amazon-s3"},{"url":"http://web.archive.org/web/20220405165313/https://stackshare.io/amazon-s3","votes":"2K","followers":"31.5K","stacks":"43.7K","time":"2022-04-05T16:53:13.000Z","tool":"amazon-s3"},{"url":"http://web.archive.org/web/20220129100445/https://stackshare.io/amazon-s3","votes":"2K","followers":"30.1K","stacks":"41.8K","time":"2022-01-29T10:04:45.000Z","tool":"amazon-s3"},{"url":"http://web.archive.org/web/20220808190407/https://www.stackshare.io/amazon-s3","votes":"2K","followers":"33.6K","stacks":"46.3K","time":"2022-08-08T19:04:07.000Z","tool":"amazon-s3"},{"url":"http://web.archive.org/web/20221224202615/https://stackshare.io/amazon-s3","votes":"2K","followers":"35.4K","stacks":"49.4K","time":"2022-12-24T20:26:15.000Z","tool":"amazon-s3"},{"url":"http://web.archive.org/web/20220714161037/https://stackshare.io/amazon-s3","votes":"2K","followers":"33.2K","stacks":"45.8K","time":"2022-07-14T16:10:37.000Z","tool":"amazon-s3"},{"url":"http://web.archive.org/web/20220413013843/https://stackshare.io/amazon-s3","votes":"2K","followers":"31.6K","stacks":"43.8K","time":"2022-04-13T01:38:43.000Z","tool":"amazon-s3"},{"url":"http://web.archive.org/web/20211019020301/https://www.stackshare.io/amazon-s3","votes":"2K","followers":"28.1K","stacks":"39.7K","time":"2021-10-19T02:03:01.000Z","tool":"amazon-s3"},{"url":"http://web.archive.org/web/20220128045920/https://stackshare.io/amazon-s3","votes":"2K","followers":"30.1K","stacks":"41.8K","time":"2022-01-28T04:59:20.000Z","tool":"amazon-s3"}]