[{"url":"http://web.archive.org/web/20200328090608/http://stackshare.io:80/github","votes":"10K","followers":"69.3K","stacks":"79K","name":"GitHub","description":"Powerful collaboration, review, and code management for open source and private development projects","time":"2020-03-28T09:06:08.000Z","tool":"github"},{"url":"http://web.archive.org/web/20200426232053/https://stackshare.io/github","votes":"10K","followers":"69.3K","stacks":"79K","name":"GitHub","description":"Powerful collaboration, review, and code management for open source and private development projects","time":"2020-04-26T23:20:53.000Z","tool":"github"},{"url":"http://web.archive.org/web/20200501130742/https://stackshare.io/github","votes":"10K","followers":"71.8K","stacks":"81.6K","name":"GitHub","description":"Powerful collaboration, review, and code management for open source and private development projects","time":"2020-05-01T13:07:42.000Z","tool":"github"},{"url":"http://web.archive.org/web/20200527183405/http://stackshare.io:80/github","votes":"10K","followers":"71.8K","stacks":"81.6K","name":"GitHub","description":"Powerful collaboration, review, and code management for open source and private development projects","time":"2020-05-27T18:34:05.000Z","tool":"github"},{"url":"http://web.archive.org/web/20200727112144/http://stackshare.io:80/github","votes":"10.1K","followers":"78.2K","stacks":"106K","image":"http://web.archive.org/web/20200809061807im_/https://img.stackshare.io/service/27/sBsvBbjY.png","name":"GitHub","description":"Powerful collaboration, review, and code management for open source and private development projects","time":"2020-07-27T11:21:44.000Z","tool":"github"},{"url":"http://web.archive.org/web/20200809061807/https://www.stackshare.io/github","votes":"10.1K","followers":"78.2K","stacks":"106K","image":"http://web.archive.org/web/20200809061807im_/https://img.stackshare.io/service/27/sBsvBbjY.png","name":"GitHub","description":"Powerful collaboration, review, and code management for open source and private development projects","time":"2020-08-09T06:18:07.000Z","tool":"github"},{"url":"http://web.archive.org/web/20200811210330/https://stackshare.io/github","votes":"10.1K","followers":"78.2K","stacks":"106.6K","image":"http://web.archive.org/web/20200811210330im_/https://img.stackshare.io/service/27/sBsvBbjY.png","name":"GitHub","description":"Powerful collaboration, review, and code management for open source and private development projects","time":"2020-08-11T21:03:30.000Z","tool":"github"},{"url":"http://web.archive.org/web/20201124041600/https://www.stackshare.io/github","votes":"10.1K","followers":"96.3K","stacks":"128.3K","image":"http://web.archive.org/web/20201124041600im_/https://img.stackshare.io/service/27/sBsvBbjY.png","name":"GitHub","description":"Powerful collaboration, review, and code management for open source and private development projects","time":"2020-11-24T04:16:00.000Z","tool":"github"},{"url":"http://web.archive.org/web/20201130202624/https://stackshare.io/github","votes":"10.1K","followers":"97.3K","stacks":"129.4K","image":"http://web.archive.org/web/20201130202624im_/https://img.stackshare.io/service/27/sBsvBbjY.png","name":"GitHub","description":"Powerful collaboration, review, and code management for open source and private development projects","time":"2020-11-30T20:26:24.000Z","tool":"github"},{"url":"http://web.archive.org/web/20210204134615/https://stackshare.io/github","votes":"10.2K","followers":"109.7K","stacks":"142K","image":"http://web.archive.org/web/20210204134615im_/https://img.stackshare.io/service/27/sBsvBbjY.png","name":"GitHub","description":"Powerful collaboration, review, and code management for open source and private development projects","time":"2021-02-04T13:46:15.000Z","tool":"github"},{"url":"http://web.archive.org/web/20210207104525/http://stackshare.io/github","votes":"10.2K","followers":"109.7K","stacks":"142K","image":"http://web.archive.org/web/20210204134615im_/https://img.stackshare.io/service/27/sBsvBbjY.png","name":"GitHub","description":"Powerful collaboration, review, and code management for open source and private development projects","time":"2021-02-07T10:45:25.000Z","tool":"github"},{"url":"http://web.archive.org/web/20210225090000/http://stackshare.io/github","votes":"10.2K","followers":"114.2K","stacks":"146.7K","image":"http://web.archive.org/web/20210225090002im_/https://img.stackshare.io/service/27/sBsvBbjY.png","name":"GitHub","description":"Powerful collaboration, review, and code management for open source and private development projects","time":"2021-02-25T09:00:00.000Z","tool":"github"},{"url":"http://web.archive.org/web/20210225090002/https://stackshare.io/github","votes":"10.2K","followers":"114.2K","stacks":"146.7K","image":"http://web.archive.org/web/20210225090002im_/https://img.stackshare.io/service/27/sBsvBbjY.png","name":"GitHub","description":"Powerful collaboration, review, and code management for open source and private development projects","time":"2021-02-25T09:00:02.000Z","tool":"github"},{"url":"http://web.archive.org/web/20210514143416/https://www.stackshare.io/github","votes":"10.2K","followers":"128.9K","stacks":"161.6K","image":"http://web.archive.org/web/20210514143416im_/https://img.stackshare.io/service/27/sBsvBbjY.png","name":"GitHub","description":"Powerful collaboration, review, and code management for open source and private development projects","time":"2021-05-14T14:34:16.000Z","tool":"github"},{"url":"http://web.archive.org/web/20210817225750/https://stackshare.io/github","votes":"10.2K","followers":"138.8K","stacks":"171.8K","image":"http://web.archive.org/web/20210817225750im_/https://img.stackshare.io/service/27/sBsvBbjY.png","name":"GitHub","description":"Powerful collaboration, review, and code management for open source and private development projects","time":"2021-08-17T22:57:50.000Z","tool":"github"},{"url":"http://web.archive.org/web/20210902040920/https://stackshare.io/github","votes":"10.2K","followers":"141.1K","stacks":"174.1K","image":"http://web.archive.org/web/20210902040920im_/https://img.stackshare.io/service/27/sBsvBbjY.png","name":"GitHub","description":"Powerful collaboration, review, and code management for open source and private development projects","time":"2021-09-02T04:09:20.000Z","tool":"github"},{"url":"http://web.archive.org/web/20211007100214/https://stackshare.io/github","votes":"10.2K","followers":"147.2K","stacks":"180.4K","image":"http://web.archive.org/web/20211007100214im_/https://img.stackshare.io/service/27/sBsvBbjY.png","name":"GitHub","description":"Powerful collaboration, review, and code management for open source and private development projects","time":"2021-10-07T10:02:14.000Z","tool":"github"},{"url":"http://web.archive.org/web/20211019032625/https://www.stackshare.io/github","votes":"10.2K","followers":"149.1K","stacks":"182.4K","image":"http://web.archive.org/web/20211019032625im_/https://img.stackshare.io/service/27/sBsvBbjY.png","name":"GitHub","description":"Powerful collaboration, review, and code management for open source and private development projects","time":"2021-10-19T03:26:25.000Z","tool":"github"},{"url":"http://web.archive.org/web/20211209081723/https://stackshare.io/github","votes":"10.2K","followers":"156.3K","stacks":"189.8K","image":"http://web.archive.org/web/20211209081723im_/https://img.stackshare.io/service/27/sBsvBbjY.png","name":"GitHub","description":"Powerful collaboration, review, and code management for open source and private development projects","time":"2021-12-09T08:17:23.000Z","tool":"github"},{"url":"http://web.archive.org/web/20220126055924/https://www.stackshare.io/github","votes":"10.2K","followers":"162.2K","stacks":"195.6K","image":"http://web.archive.org/web/20220126055924im_/https://img.stackshare.io/service/27/default_869c34d29acc794d60ecdd5d2b5bfc042a80a4ec.jpg","name":"GitHub","description":"Powerful collaboration, review, and code management for open source and private development projects","time":"2022-01-26T05:59:24.000Z","tool":"github"},{"url":"http://web.archive.org/web/20220129120038/https://stackshare.io/github","votes":"10.2K","followers":"162.6K","stacks":"195.9K","image":"http://web.archive.org/web/20220129120038im_/https://img.stackshare.io/service/27/default_869c34d29acc794d60ecdd5d2b5bfc042a80a4ec.jpg","name":"GitHub","description":"Powerful collaboration, review, and code management for open source and private development projects","time":"2022-01-29T12:00:38.000Z","tool":"github"},{"url":"http://web.archive.org/web/20220309094306/https://stackshare.io/github","votes":"10.2K","followers":"168.2K","stacks":"201.6K","image":"http://web.archive.org/web/20220309094306im_/https://img.stackshare.io/service/27/default_869c34d29acc794d60ecdd5d2b5bfc042a80a4ec.jpg","name":"GitHub","description":"Powerful collaboration, review, and code management for open source and private development projects","time":"2022-03-09T09:43:06.000Z","tool":"github"},{"url":"http://web.archive.org/web/20220314073638/https://www.stackshare.io/github","votes":"10.2K","followers":"168.9K","stacks":"202.7K","image":"http://web.archive.org/web/20220314073638im_/https://img.stackshare.io/service/27/default_869c34d29acc794d60ecdd5d2b5bfc042a80a4ec.jpg","name":"GitHub","description":"Powerful collaboration, review, and code management for open source and private development projects","time":"2022-03-14T07:36:38.000Z","tool":"github"},{"url":"http://web.archive.org/web/20220412140453/https://stackshare.io/github","votes":"10.2K","followers":"173.8K","stacks":"207.6K","image":"http://web.archive.org/web/20220412140453im_/https://img.stackshare.io/service/27/default_869c34d29acc794d60ecdd5d2b5bfc042a80a4ec.jpg","name":"GitHub","description":"Powerful collaboration, review, and code management for open source and private development projects","time":"2022-04-12T14:04:53.000Z","tool":"github"},{"url":"http://web.archive.org/web/20220418062905/http://stackshare.io/github","votes":"10.2K","followers":"173.8K","stacks":"207.6K","image":"http://web.archive.org/web/20220412140453im_/https://img.stackshare.io/service/27/default_869c34d29acc794d60ecdd5d2b5bfc042a80a4ec.jpg","name":"GitHub","description":"Powerful collaboration, review, and code management for open source and private development projects","time":"2022-04-18T06:29:05.000Z","tool":"github"},{"url":"http://web.archive.org/web/20220425014831/https://stackshare.io/github","votes":"10.2K","followers":"175.5K","stacks":"209.1K","image":"http://web.archive.org/web/20220425014831im_/https://img.stackshare.io/service/27/default_869c34d29acc794d60ecdd5d2b5bfc042a80a4ec.jpg","name":"GitHub","description":"Powerful collaboration, review, and code management for open source and private development projects","time":"2022-04-25T01:48:31.000Z","tool":"github"},{"url":"http://web.archive.org/web/20220425044750/https://stackshare.io/github","votes":"10.2K","followers":"175.5K","stacks":"209.1K","image":"http://web.archive.org/web/20220425044750im_/https://img.stackshare.io/service/27/default_869c34d29acc794d60ecdd5d2b5bfc042a80a4ec.jpg","name":"GitHub","description":"Powerful collaboration, review, and code management for open source and private development projects","time":"2022-04-25T04:47:50.000Z","tool":"github"},{"url":"http://web.archive.org/web/20220516210204/https://stackshare.io/github","votes":"10.2K","followers":"178.9K","stacks":"212.8K","image":"http://web.archive.org/web/20220516210204im_/https://img.stackshare.io/service/27/default_869c34d29acc794d60ecdd5d2b5bfc042a80a4ec.jpg","name":"GitHub","description":"Powerful collaboration, review, and code management for open source and private development projects","time":"2022-05-16T21:02:04.000Z","tool":"github"},{"url":"http://web.archive.org/web/20220618213846/https://stackshare.io/github","votes":"10.2K","followers":"183.8K","stacks":"217.8K","image":"http://web.archive.org/web/20220618213846im_/https://img.stackshare.io/service/27/default_869c34d29acc794d60ecdd5d2b5bfc042a80a4ec.jpg","name":"GitHub","description":"Powerful collaboration, review, and code management for open source and private development projects","time":"2022-06-18T21:38:46.000Z","tool":"github"},{"url":"http://web.archive.org/web/20220713222850/https://stackshare.io/github","votes":"10.2K","followers":"187.4K","stacks":"221.5K","image":"http://web.archive.org/web/20220713222850im_/https://img.stackshare.io/service/27/default_869c34d29acc794d60ecdd5d2b5bfc042a80a4ec.jpg","name":"GitHub","description":"Powerful collaboration, review, and code management for open source and private development projects","time":"2022-07-13T22:28:50.000Z","tool":"github"},{"url":"http://web.archive.org/web/20220808202828/https://www.stackshare.io/github","votes":"10.2K","followers":"190.9K","stacks":"225K","image":"http://web.archive.org/web/20220808202828im_/https://img.stackshare.io/service/27/default_869c34d29acc794d60ecdd5d2b5bfc042a80a4ec.jpg","name":"GitHub","description":"Powerful collaboration, review, and code management for open source and private development projects","time":"2022-08-08T20:28:28.000Z","tool":"github"},{"url":"http://web.archive.org/web/20220820222606/https://stackshare.io/github","votes":"10.2K","followers":"192.5K","stacks":"226.7K","image":"http://web.archive.org/web/20220820222606im_/https://img.stackshare.io/service/27/default_869c34d29acc794d60ecdd5d2b5bfc042a80a4ec.jpg","name":"GitHub","description":"Powerful collaboration, review, and code management for open source and private development projects","time":"2022-08-20T22:26:06.000Z","tool":"github"},{"url":"http://web.archive.org/web/20220820222606/http://stackshare.io/github","votes":"10.2K","followers":"192.5K","stacks":"226.7K","image":"http://web.archive.org/web/20220820222606im_/https://img.stackshare.io/service/27/default_869c34d29acc794d60ecdd5d2b5bfc042a80a4ec.jpg","name":"GitHub","description":"Powerful collaboration, review, and code management for open source and private development projects","time":"2022-08-20T22:26:06.000Z","tool":"github"},{"url":"http://web.archive.org/web/20221001015209/https://stackshare.io/github","votes":"10.2K","followers":"197.4K","stacks":"231.7K","image":"http://web.archive.org/web/20221001015209im_/https://img.stackshare.io/service/27/default_869c34d29acc794d60ecdd5d2b5bfc042a80a4ec.jpg","name":"GitHub","description":"Powerful collaboration, review, and code management for open source and private development projects","time":"2022-10-01T01:52:09.000Z","tool":"github"},{"url":"http://web.archive.org/web/20221009170747/https://stackshare.io/github","votes":"10.2K","followers":"198K","stacks":"232.4K","image":"http://web.archive.org/web/20221009170747im_/https://img.stackshare.io/service/27/default_869c34d29acc794d60ecdd5d2b5bfc042a80a4ec.jpg","name":"GitHub","description":"Powerful collaboration, review, and code management for open source and private development projects","time":"2022-10-09T17:07:47.000Z","tool":"github"},{"url":"http://web.archive.org/web/20221202161515/https://stackshare.io/github","votes":"10.2K","followers":"204.3K","stacks":"238.7K","image":"http://web.archive.org/web/20221202161515im_/https://img.stackshare.io/service/27/default_869c34d29acc794d60ecdd5d2b5bfc042a80a4ec.jpg","name":"GitHub","description":"Powerful collaboration, review, and code management for open source and private development projects","time":"2022-12-02T16:15:15.000Z","tool":"github"},{"url":"https://stackshare.io/github","votes":"10.2K","followers":"211.3K","stacks":"245.9K","image":"https://img.stackshare.io/service/27/default_869c34d29acc794d60ecdd5d2b5bfc042a80a4ec.jpg","name":"GitHub","description":"Powerful collaboration, review, and code management for open source and private development projects","time":"2023-02-08T15:15:36.950Z","tool":"github"}]